{
    "description": "",
    "tags": [],
    "size": {
        "height": 1440,
        "width": 1920
    },
    "objects": [
        {
            "id": 16355786,
            "classId": 28372,
            "description": "",
            "geometryType": "polygon",
            "labelerLogin": "seryios.sych@gmail.com",
            "createdAt": "2023-08-06T16:57:10.882Z",
            "updatedAt": "2023-08-06T16:57:10.882Z",
            "tags": [],
            "classTitle": "apple_red_boskoop",
            "points": {
                "exterior": [
                    [
                        751,
                        195
                    ],
                    [
                        750,
                        196
                    ],
                    [
                        741,
                        196
                    ],
                    [
                        740,
                        197
                    ],
                    [
                        731,
                        197
                    ],
                    [
                        730,
                        198
                    ],
                    [
                        724,
                        198
                    ],
                    [
                        723,
                        199
                    ],
                    [
                        721,
                        199
                    ],
                    [
                        720,
                        200
                    ],
                    [
                        718,
                        200
                    ],
                    [
                        717,
                        201
                    ],
                    [
                        715,
                        201
                    ],
                    [
                        714,
                        202
                    ],
                    [
                        712,
                        202
                    ],
                    [
                        711,
                        203
                    ],
                    [
                        709,
                        203
                    ],
                    [
                        708,
                        204
                    ],
                    [
                        706,
                        204
                    ],
                    [
                        705,
                        205
                    ],
                    [
                        703,
                        205
                    ],
                    [
                        702,
                        206
                    ],
                    [
                        700,
                        206
                    ],
                    [
                        699,
                        207
                    ],
                    [
                        697,
                        207
                    ],
                    [
                        696,
                        208
                    ],
                    [
                        695,
                        208
                    ],
                    [
                        682,
                        221
                    ],
                    [
                        681,
                        221
                    ],
                    [
                        668,
                        234
                    ],
                    [
                        668,
                        235
                    ],
                    [
                        665,
                        238
                    ],
                    [
                        665,
                        239
                    ],
                    [
                        663,
                        241
                    ],
                    [
                        663,
                        242
                    ],
                    [
                        661,
                        244
                    ],
                    [
                        661,
                        245
                    ],
                    [
                        658,
                        248
                    ],
                    [
                        658,
                        249
                    ],
                    [
                        656,
                        251
                    ],
                    [
                        656,
                        252
                    ],
                    [
                        654,
                        254
                    ],
                    [
                        654,
                        255
                    ],
                    [
                        651,
                        258
                    ],
                    [
                        651,
                        259
                    ],
                    [
                        649,
                        261
                    ],
                    [
                        649,
                        262
                    ],
                    [
                        648,
                        263
                    ],
                    [
                        648,
                        264
                    ],
                    [
                        647,
                        265
                    ],
                    [
                        647,
                        267
                    ],
                    [
                        646,
                        268
                    ],
                    [
                        646,
                        269
                    ],
                    [
                        645,
                        270
                    ],
                    [
                        645,
                        272
                    ],
                    [
                        644,
                        273
                    ],
                    [
                        644,
                        275
                    ],
                    [
                        643,
                        276
                    ],
                    [
                        643,
                        278
                    ],
                    [
                        642,
                        279
                    ],
                    [
                        642,
                        280
                    ],
                    [
                        641,
                        281
                    ],
                    [
                        641,
                        283
                    ],
                    [
                        640,
                        284
                    ],
                    [
                        640,
                        286
                    ],
                    [
                        639,
                        287
                    ],
                    [
                        639,
                        288
                    ],
                    [
                        638,
                        289
                    ],
                    [
                        638,
                        291
                    ],
                    [
                        637,
                        292
                    ],
                    [
                        637,
                        299
                    ],
                    [
                        636,
                        300
                    ],
                    [
                        636,
                        311
                    ],
                    [
                        635,
                        312
                    ],
                    [
                        635,
                        323
                    ],
                    [
                        634,
                        324
                    ],
                    [
                        634,
                        331
                    ],
                    [
                        635,
                        332
                    ],
                    [
                        635,
                        335
                    ],
                    [
                        636,
                        336
                    ],
                    [
                        636,
                        338
                    ],
                    [
                        637,
                        339
                    ],
                    [
                        637,
                        342
                    ],
                    [
                        638,
                        343
                    ],
                    [
                        638,
                        346
                    ],
                    [
                        639,
                        347
                    ],
                    [
                        639,
                        349
                    ],
                    [
                        640,
                        350
                    ],
                    [
                        640,
                        353
                    ],
                    [
                        641,
                        354
                    ],
                    [
                        641,
                        356
                    ],
                    [
                        642,
                        357
                    ],
                    [
                        642,
                        360
                    ],
                    [
                        643,
                        361
                    ],
                    [
                        643,
                        363
                    ],
                    [
                        644,
                        364
                    ],
                    [
                        644,
                        365
                    ],
                    [
                        645,
                        366
                    ],
                    [
                        645,
                        367
                    ],
                    [
                        646,
                        368
                    ],
                    [
                        646,
                        369
                    ],
                    [
                        647,
                        370
                    ],
                    [
                        647,
                        371
                    ],
                    [
                        648,
                        372
                    ],
                    [
                        648,
                        373
                    ],
                    [
                        649,
                        374
                    ],
                    [
                        649,
                        375
                    ],
                    [
                        650,
                        376
                    ],
                    [
                        650,
                        377
                    ],
                    [
                        651,
                        378
                    ],
                    [
                        651,
                        379
                    ],
                    [
                        652,
                        380
                    ],
                    [
                        652,
                        381
                    ],
                    [
                        653,
                        382
                    ],
                    [
                        653,
                        383
                    ],
                    [
                        654,
                        384
                    ],
                    [
                        654,
                        385
                    ],
                    [
                        655,
                        386
                    ],
                    [
                        655,
                        387
                    ],
                    [
                        657,
                        389
                    ],
                    [
                        657,
                        390
                    ],
                    [
                        659,
                        392
                    ],
                    [
                        659,
                        393
                    ],
                    [
                        661,
                        395
                    ],
                    [
                        661,
                        396
                    ],
                    [
                        663,
                        398
                    ],
                    [
                        663,
                        399
                    ],
                    [
                        665,
                        401
                    ],
                    [
                        665,
                        402
                    ],
                    [
                        667,
                        404
                    ],
                    [
                        667,
                        405
                    ],
                    [
                        669,
                        407
                    ],
                    [
                        669,
                        408
                    ],
                    [
                        671,
                        410
                    ],
                    [
                        671,
                        411
                    ],
                    [
                        673,
                        413
                    ],
                    [
                        673,
                        414
                    ],
                    [
                        676,
                        417
                    ],
                    [
                        677,
                        417
                    ],
                    [
                        680,
                        420
                    ],
                    [
                        681,
                        420
                    ],
                    [
                        685,
                        424
                    ],
                    [
                        686,
                        424
                    ],
                    [
                        690,
                        428
                    ],
                    [
                        691,
                        428
                    ],
                    [
                        694,
                        431
                    ],
                    [
                        695,
                        431
                    ],
                    [
                        697,
                        433
                    ],
                    [
                        698,
                        433
                    ],
                    [
                        699,
                        434
                    ],
                    [
                        700,
                        434
                    ],
                    [
                        701,
                        435
                    ],
                    [
                        703,
                        435
                    ],
                    [
                        704,
                        436
                    ],
                    [
                        705,
                        436
                    ],
                    [
                        706,
                        437
                    ],
                    [
                        707,
                        437
                    ],
                    [
                        708,
                        438
                    ],
                    [
                        710,
                        438
                    ],
                    [
                        711,
                        439
                    ],
                    [
                        712,
                        439
                    ],
                    [
                        713,
                        440
                    ],
                    [
                        715,
                        440
                    ],
                    [
                        716,
                        441
                    ],
                    [
                        717,
                        441
                    ],
                    [
                        718,
                        442
                    ],
                    [
                        720,
                        442
                    ],
                    [
                        721,
                        443
                    ],
                    [
                        722,
                        443
                    ],
                    [
                        723,
                        444
                    ],
                    [
                        724,
                        444
                    ],
                    [
                        725,
                        445
                    ],
                    [
                        727,
                        445
                    ],
                    [
                        728,
                        446
                    ],
                    [
                        729,
                        446
                    ],
                    [
                        730,
                        447
                    ],
                    [
                        734,
                        447
                    ],
                    [
                        735,
                        448
                    ],
                    [
                        742,
                        448
                    ],
                    [
                        743,
                        449
                    ],
                    [
                        750,
                        449
                    ],
                    [
                        751,
                        450
                    ],
                    [
                        758,
                        450
                    ],
                    [
                        759,
                        451
                    ],
                    [
                        766,
                        451
                    ],
                    [
                        767,
                        452
                    ],
                    [
                        780,
                        452
                    ],
                    [
                        781,
                        453
                    ],
                    [
                        802,
                        453
                    ],
                    [
                        803,
                        454
                    ],
                    [
                        815,
                        454
                    ],
                    [
                        816,
                        453
                    ],
                    [
                        820,
                        453
                    ],
                    [
                        821,
                        452
                    ],
                    [
                        825,
                        452
                    ],
                    [
                        826,
                        451
                    ],
                    [
                        830,
                        451
                    ],
                    [
                        831,
                        450
                    ],
                    [
                        833,
                        450
                    ],
                    [
                        834,
                        449
                    ],
                    [
                        835,
                        449
                    ],
                    [
                        837,
                        447
                    ],
                    [
                        838,
                        447
                    ],
                    [
                        840,
                        445
                    ],
                    [
                        841,
                        445
                    ],
                    [
                        843,
                        443
                    ],
                    [
                        844,
                        443
                    ],
                    [
                        847,
                        440
                    ],
                    [
                        848,
                        440
                    ],
                    [
                        850,
                        438
                    ],
                    [
                        851,
                        438
                    ],
                    [
                        853,
                        436
                    ],
                    [
                        854,
                        436
                    ],
                    [
                        856,
                        434
                    ],
                    [
                        857,
                        434
                    ],
                    [
                        859,
                        432
                    ],
                    [
                        860,
                        432
                    ],
                    [
                        870,
                        422
                    ],
                    [
                        871,
                        422
                    ],
                    [
                        880,
                        413
                    ],
                    [
                        880,
                        412
                    ],
                    [
                        881,
                        411
                    ],
                    [
                        881,
                        410
                    ],
                    [
                        882,
                        409
                    ],
                    [
                        882,
                        408
                    ],
                    [
                        883,
                        407
                    ],
                    [
                        883,
                        405
                    ],
                    [
                        884,
                        404
                    ],
                    [
                        884,
                        403
                    ],
                    [
                        885,
                        402
                    ],
                    [
                        885,
                        400
                    ],
                    [
                        886,
                        399
                    ],
                    [
                        886,
                        398
                    ],
                    [
                        887,
                        397
                    ],
                    [
                        887,
                        396
                    ],
                    [
                        888,
                        395
                    ],
                    [
                        888,
                        393
                    ],
                    [
                        889,
                        392
                    ],
                    [
                        889,
                        391
                    ],
                    [
                        890,
                        390
                    ],
                    [
                        890,
                        389
                    ],
                    [
                        891,
                        388
                    ],
                    [
                        891,
                        386
                    ],
                    [
                        892,
                        385
                    ],
                    [
                        892,
                        384
                    ],
                    [
                        893,
                        383
                    ],
                    [
                        893,
                        382
                    ],
                    [
                        894,
                        381
                    ],
                    [
                        894,
                        379
                    ],
                    [
                        895,
                        378
                    ],
                    [
                        895,
                        377
                    ],
                    [
                        896,
                        376
                    ],
                    [
                        896,
                        374
                    ],
                    [
                        897,
                        373
                    ],
                    [
                        897,
                        372
                    ],
                    [
                        898,
                        371
                    ],
                    [
                        898,
                        370
                    ],
                    [
                        899,
                        369
                    ],
                    [
                        899,
                        367
                    ],
                    [
                        900,
                        366
                    ],
                    [
                        900,
                        365
                    ],
                    [
                        901,
                        364
                    ],
                    [
                        901,
                        363
                    ],
                    [
                        902,
                        362
                    ],
                    [
                        902,
                        350
                    ],
                    [
                        903,
                        349
                    ],
                    [
                        903,
                        328
                    ],
                    [
                        904,
                        327
                    ],
                    [
                        904,
                        315
                    ],
                    [
                        903,
                        314
                    ],
                    [
                        903,
                        312
                    ],
                    [
                        902,
                        311
                    ],
                    [
                        902,
                        309
                    ],
                    [
                        901,
                        308
                    ],
                    [
                        901,
                        307
                    ],
                    [
                        900,
                        306
                    ],
                    [
                        900,
                        304
                    ],
                    [
                        899,
                        303
                    ],
                    [
                        899,
                        301
                    ],
                    [
                        898,
                        300
                    ],
                    [
                        898,
                        298
                    ],
                    [
                        897,
                        297
                    ],
                    [
                        897,
                        295
                    ],
                    [
                        896,
                        294
                    ],
                    [
                        896,
                        293
                    ],
                    [
                        895,
                        292
                    ],
                    [
                        895,
                        290
                    ],
                    [
                        894,
                        289
                    ],
                    [
                        894,
                        287
                    ],
                    [
                        893,
                        286
                    ],
                    [
                        893,
                        284
                    ],
                    [
                        892,
                        283
                    ],
                    [
                        892,
                        281
                    ],
                    [
                        891,
                        280
                    ],
                    [
                        891,
                        279
                    ],
                    [
                        890,
                        278
                    ],
                    [
                        890,
                        276
                    ],
                    [
                        889,
                        275
                    ],
                    [
                        889,
                        274
                    ],
                    [
                        885,
                        270
                    ],
                    [
                        885,
                        269
                    ],
                    [
                        878,
                        262
                    ],
                    [
                        878,
                        261
                    ],
                    [
                        870,
                        253
                    ],
                    [
                        870,
                        252
                    ],
                    [
                        863,
                        245
                    ],
                    [
                        863,
                        244
                    ],
                    [
                        858,
                        239
                    ],
                    [
                        857,
                        239
                    ],
                    [
                        855,
                        237
                    ],
                    [
                        854,
                        237
                    ],
                    [
                        852,
                        235
                    ],
                    [
                        851,
                        235
                    ],
                    [
                        849,
                        233
                    ],
                    [
                        848,
                        233
                    ],
                    [
                        846,
                        231
                    ],
                    [
                        845,
                        231
                    ],
                    [
                        843,
                        229
                    ],
                    [
                        842,
                        229
                    ],
                    [
                        840,
                        227
                    ],
                    [
                        839,
                        227
                    ],
                    [
                        837,
                        225
                    ],
                    [
                        836,
                        225
                    ],
                    [
                        835,
                        224
                    ],
                    [
                        834,
                        224
                    ],
                    [
                        832,
                        222
                    ],
                    [
                        831,
                        222
                    ],
                    [
                        829,
                        220
                    ],
                    [
                        828,
                        220
                    ],
                    [
                        826,
                        218
                    ],
                    [
                        825,
                        218
                    ],
                    [
                        823,
                        216
                    ],
                    [
                        822,
                        216
                    ],
                    [
                        820,
                        214
                    ],
                    [
                        819,
                        214
                    ],
                    [
                        817,
                        212
                    ],
                    [
                        816,
                        212
                    ],
                    [
                        814,
                        210
                    ],
                    [
                        813,
                        210
                    ],
                    [
                        812,
                        209
                    ],
                    [
                        811,
                        209
                    ],
                    [
                        810,
                        208
                    ],
                    [
                        809,
                        208
                    ],
                    [
                        808,
                        207
                    ],
                    [
                        806,
                        207
                    ],
                    [
                        805,
                        206
                    ],
                    [
                        804,
                        206
                    ],
                    [
                        803,
                        205
                    ],
                    [
                        801,
                        205
                    ],
                    [
                        800,
                        204
                    ],
                    [
                        799,
                        204
                    ],
                    [
                        798,
                        203
                    ],
                    [
                        797,
                        203
                    ],
                    [
                        796,
                        202
                    ],
                    [
                        794,
                        202
                    ],
                    [
                        793,
                        201
                    ],
                    [
                        792,
                        201
                    ],
                    [
                        791,
                        200
                    ],
                    [
                        789,
                        200
                    ],
                    [
                        788,
                        199
                    ],
                    [
                        787,
                        199
                    ],
                    [
                        786,
                        198
                    ],
                    [
                        781,
                        198
                    ],
                    [
                        780,
                        197
                    ],
                    [
                        771,
                        197
                    ],
                    [
                        770,
                        196
                    ],
                    [
                        761,
                        196
                    ],
                    [
                        760,
                        195
                    ]
                ],
                "interior": []
            }
        },
        {
            "id": 16355785,
            "classId": 28372,
            "description": "",
            "geometryType": "rectangle",
            "labelerLogin": "seryios.sych@gmail.com",
            "createdAt": "2023-08-06T16:57:10.881Z",
            "updatedAt": "2023-08-06T16:57:10.881Z",
            "tags": [],
            "classTitle": "apple_red_boskoop",
            "points": {
                "exterior": [
                    [
                        634,
                        195
                    ],
                    [
                        905,
                        455
                    ]
                ],
                "interior": []
            }
        },
        {
            "id": 16355784,
            "classId": 28372,
            "description": "",
            "geometryType": "polygon",
            "labelerLogin": "seryios.sych@gmail.com",
            "createdAt": "2023-08-06T16:57:10.881Z",
            "updatedAt": "2023-08-06T16:57:10.881Z",
            "tags": [],
            "classTitle": "apple_red_boskoop",
            "points": {
                "exterior": [
                    [
                        1315,
                        925
                    ],
                    [
                        1314,
                        926
                    ],
                    [
                        1296,
                        926
                    ],
                    [
                        1295,
                        927
                    ],
                    [
                        1293,
                        927
                    ],
                    [
                        1292,
                        928
                    ],
                    [
                        1290,
                        928
                    ],
                    [
                        1289,
                        929
                    ],
                    [
                        1288,
                        929
                    ],
                    [
                        1287,
                        930
                    ],
                    [
                        1285,
                        930
                    ],
                    [
                        1284,
                        931
                    ],
                    [
                        1282,
                        931
                    ],
                    [
                        1281,
                        932
                    ],
                    [
                        1279,
                        932
                    ],
                    [
                        1278,
                        933
                    ],
                    [
                        1276,
                        933
                    ],
                    [
                        1275,
                        934
                    ],
                    [
                        1273,
                        934
                    ],
                    [
                        1272,
                        935
                    ],
                    [
                        1270,
                        935
                    ],
                    [
                        1269,
                        936
                    ],
                    [
                        1268,
                        936
                    ],
                    [
                        1267,
                        937
                    ],
                    [
                        1265,
                        937
                    ],
                    [
                        1264,
                        938
                    ],
                    [
                        1262,
                        938
                    ],
                    [
                        1261,
                        939
                    ],
                    [
                        1260,
                        939
                    ],
                    [
                        1257,
                        942
                    ],
                    [
                        1256,
                        942
                    ],
                    [
                        1249,
                        949
                    ],
                    [
                        1248,
                        949
                    ],
                    [
                        1242,
                        955
                    ],
                    [
                        1241,
                        955
                    ],
                    [
                        1234,
                        962
                    ],
                    [
                        1233,
                        962
                    ],
                    [
                        1229,
                        966
                    ],
                    [
                        1229,
                        967
                    ],
                    [
                        1228,
                        968
                    ],
                    [
                        1228,
                        969
                    ],
                    [
                        1227,
                        970
                    ],
                    [
                        1227,
                        971
                    ],
                    [
                        1226,
                        972
                    ],
                    [
                        1226,
                        973
                    ],
                    [
                        1224,
                        975
                    ],
                    [
                        1224,
                        976
                    ],
                    [
                        1223,
                        977
                    ],
                    [
                        1223,
                        978
                    ],
                    [
                        1222,
                        979
                    ],
                    [
                        1222,
                        980
                    ],
                    [
                        1220,
                        982
                    ],
                    [
                        1220,
                        983
                    ],
                    [
                        1219,
                        984
                    ],
                    [
                        1219,
                        985
                    ],
                    [
                        1218,
                        986
                    ],
                    [
                        1218,
                        987
                    ],
                    [
                        1217,
                        988
                    ],
                    [
                        1217,
                        989
                    ],
                    [
                        1216,
                        990
                    ],
                    [
                        1216,
                        991
                    ],
                    [
                        1215,
                        992
                    ],
                    [
                        1215,
                        994
                    ],
                    [
                        1214,
                        995
                    ],
                    [
                        1214,
                        997
                    ],
                    [
                        1213,
                        998
                    ],
                    [
                        1213,
                        1000
                    ],
                    [
                        1212,
                        1001
                    ],
                    [
                        1212,
                        1003
                    ],
                    [
                        1211,
                        1004
                    ],
                    [
                        1211,
                        1006
                    ],
                    [
                        1210,
                        1007
                    ],
                    [
                        1210,
                        1009
                    ],
                    [
                        1209,
                        1010
                    ],
                    [
                        1209,
                        1012
                    ],
                    [
                        1208,
                        1013
                    ],
                    [
                        1208,
                        1035
                    ],
                    [
                        1209,
                        1036
                    ],
                    [
                        1209,
                        1058
                    ],
                    [
                        1210,
                        1059
                    ],
                    [
                        1210,
                        1061
                    ],
                    [
                        1211,
                        1062
                    ],
                    [
                        1211,
                        1064
                    ],
                    [
                        1212,
                        1065
                    ],
                    [
                        1212,
                        1067
                    ],
                    [
                        1213,
                        1068
                    ],
                    [
                        1213,
                        1071
                    ],
                    [
                        1214,
                        1072
                    ],
                    [
                        1214,
                        1074
                    ],
                    [
                        1215,
                        1075
                    ],
                    [
                        1215,
                        1077
                    ],
                    [
                        1216,
                        1078
                    ],
                    [
                        1216,
                        1080
                    ],
                    [
                        1217,
                        1081
                    ],
                    [
                        1217,
                        1083
                    ],
                    [
                        1218,
                        1084
                    ],
                    [
                        1218,
                        1086
                    ],
                    [
                        1219,
                        1087
                    ],
                    [
                        1219,
                        1089
                    ],
                    [
                        1220,
                        1090
                    ],
                    [
                        1220,
                        1093
                    ],
                    [
                        1221,
                        1094
                    ],
                    [
                        1221,
                        1096
                    ],
                    [
                        1222,
                        1097
                    ],
                    [
                        1222,
                        1099
                    ],
                    [
                        1223,
                        1100
                    ],
                    [
                        1223,
                        1102
                    ],
                    [
                        1224,
                        1103
                    ],
                    [
                        1224,
                        1104
                    ],
                    [
                        1230,
                        1110
                    ],
                    [
                        1230,
                        1111
                    ],
                    [
                        1242,
                        1123
                    ],
                    [
                        1242,
                        1124
                    ],
                    [
                        1249,
                        1131
                    ],
                    [
                        1250,
                        1131
                    ],
                    [
                        1251,
                        1132
                    ],
                    [
                        1252,
                        1132
                    ],
                    [
                        1254,
                        1134
                    ],
                    [
                        1255,
                        1134
                    ],
                    [
                        1257,
                        1136
                    ],
                    [
                        1258,
                        1136
                    ],
                    [
                        1259,
                        1137
                    ],
                    [
                        1260,
                        1137
                    ],
                    [
                        1262,
                        1139
                    ],
                    [
                        1263,
                        1139
                    ],
                    [
                        1264,
                        1140
                    ],
                    [
                        1265,
                        1140
                    ],
                    [
                        1267,
                        1142
                    ],
                    [
                        1268,
                        1142
                    ],
                    [
                        1269,
                        1143
                    ],
                    [
                        1270,
                        1143
                    ],
                    [
                        1272,
                        1145
                    ],
                    [
                        1273,
                        1145
                    ],
                    [
                        1275,
                        1147
                    ],
                    [
                        1276,
                        1147
                    ],
                    [
                        1277,
                        1148
                    ],
                    [
                        1278,
                        1148
                    ],
                    [
                        1279,
                        1149
                    ],
                    [
                        1280,
                        1149
                    ],
                    [
                        1281,
                        1150
                    ],
                    [
                        1284,
                        1150
                    ],
                    [
                        1285,
                        1151
                    ],
                    [
                        1287,
                        1151
                    ],
                    [
                        1288,
                        1152
                    ],
                    [
                        1291,
                        1152
                    ],
                    [
                        1292,
                        1153
                    ],
                    [
                        1295,
                        1153
                    ],
                    [
                        1296,
                        1154
                    ],
                    [
                        1298,
                        1154
                    ],
                    [
                        1299,
                        1155
                    ],
                    [
                        1302,
                        1155
                    ],
                    [
                        1303,
                        1156
                    ],
                    [
                        1312,
                        1156
                    ],
                    [
                        1313,
                        1157
                    ],
                    [
                        1328,
                        1157
                    ],
                    [
                        1329,
                        1158
                    ],
                    [
                        1337,
                        1158
                    ],
                    [
                        1338,
                        1157
                    ],
                    [
                        1340,
                        1157
                    ],
                    [
                        1341,
                        1156
                    ],
                    [
                        1342,
                        1156
                    ],
                    [
                        1343,
                        1155
                    ],
                    [
                        1345,
                        1155
                    ],
                    [
                        1346,
                        1154
                    ],
                    [
                        1348,
                        1154
                    ],
                    [
                        1349,
                        1153
                    ],
                    [
                        1350,
                        1153
                    ],
                    [
                        1351,
                        1152
                    ],
                    [
                        1353,
                        1152
                    ],
                    [
                        1354,
                        1151
                    ],
                    [
                        1356,
                        1151
                    ],
                    [
                        1357,
                        1150
                    ],
                    [
                        1358,
                        1150
                    ],
                    [
                        1359,
                        1149
                    ],
                    [
                        1361,
                        1149
                    ],
                    [
                        1362,
                        1148
                    ],
                    [
                        1364,
                        1148
                    ],
                    [
                        1365,
                        1147
                    ],
                    [
                        1366,
                        1147
                    ],
                    [
                        1367,
                        1146
                    ],
                    [
                        1368,
                        1146
                    ],
                    [
                        1371,
                        1143
                    ],
                    [
                        1372,
                        1143
                    ],
                    [
                        1378,
                        1137
                    ],
                    [
                        1379,
                        1137
                    ],
                    [
                        1386,
                        1130
                    ],
                    [
                        1387,
                        1130
                    ],
                    [
                        1393,
                        1124
                    ],
                    [
                        1394,
                        1124
                    ],
                    [
                        1398,
                        1120
                    ],
                    [
                        1398,
                        1119
                    ],
                    [
                        1399,
                        1118
                    ],
                    [
                        1399,
                        1117
                    ],
                    [
                        1400,
                        1116
                    ],
                    [
                        1400,
                        1115
                    ],
                    [
                        1402,
                        1113
                    ],
                    [
                        1402,
                        1112
                    ],
                    [
                        1403,
                        1111
                    ],
                    [
                        1403,
                        1110
                    ],
                    [
                        1404,
                        1109
                    ],
                    [
                        1404,
                        1108
                    ],
                    [
                        1406,
                        1106
                    ],
                    [
                        1406,
                        1105
                    ],
                    [
                        1407,
                        1104
                    ],
                    [
                        1407,
                        1103
                    ],
                    [
                        1408,
                        1102
                    ],
                    [
                        1408,
                        1101
                    ],
                    [
                        1410,
                        1099
                    ],
                    [
                        1410,
                        1098
                    ],
                    [
                        1411,
                        1097
                    ],
                    [
                        1411,
                        1096
                    ],
                    [
                        1412,
                        1095
                    ],
                    [
                        1412,
                        1094
                    ],
                    [
                        1413,
                        1093
                    ],
                    [
                        1413,
                        1089
                    ],
                    [
                        1414,
                        1088
                    ],
                    [
                        1414,
                        1080
                    ],
                    [
                        1415,
                        1079
                    ],
                    [
                        1415,
                        1058
                    ],
                    [
                        1416,
                        1057
                    ],
                    [
                        1416,
                        1038
                    ],
                    [
                        1415,
                        1037
                    ],
                    [
                        1415,
                        1033
                    ],
                    [
                        1414,
                        1032
                    ],
                    [
                        1414,
                        1028
                    ],
                    [
                        1413,
                        1027
                    ],
                    [
                        1413,
                        1023
                    ],
                    [
                        1412,
                        1022
                    ],
                    [
                        1412,
                        1018
                    ],
                    [
                        1411,
                        1017
                    ],
                    [
                        1411,
                        1013
                    ],
                    [
                        1410,
                        1012
                    ],
                    [
                        1410,
                        1008
                    ],
                    [
                        1409,
                        1007
                    ],
                    [
                        1409,
                        1003
                    ],
                    [
                        1408,
                        1002
                    ],
                    [
                        1408,
                        998
                    ],
                    [
                        1407,
                        997
                    ],
                    [
                        1407,
                        994
                    ],
                    [
                        1406,
                        993
                    ],
                    [
                        1406,
                        991
                    ],
                    [
                        1405,
                        990
                    ],
                    [
                        1405,
                        989
                    ],
                    [
                        1404,
                        988
                    ],
                    [
                        1404,
                        986
                    ],
                    [
                        1403,
                        985
                    ],
                    [
                        1403,
                        983
                    ],
                    [
                        1402,
                        982
                    ],
                    [
                        1402,
                        981
                    ],
                    [
                        1401,
                        980
                    ],
                    [
                        1401,
                        978
                    ],
                    [
                        1400,
                        977
                    ],
                    [
                        1400,
                        975
                    ],
                    [
                        1399,
                        974
                    ],
                    [
                        1399,
                        973
                    ],
                    [
                        1398,
                        972
                    ],
                    [
                        1398,
                        970
                    ],
                    [
                        1397,
                        969
                    ],
                    [
                        1397,
                        967
                    ],
                    [
                        1396,
                        966
                    ],
                    [
                        1396,
                        965
                    ],
                    [
                        1395,
                        964
                    ],
                    [
                        1395,
                        962
                    ],
                    [
                        1394,
                        961
                    ],
                    [
                        1394,
                        960
                    ],
                    [
                        1392,
                        958
                    ],
                    [
                        1391,
                        958
                    ],
                    [
                        1388,
                        955
                    ],
                    [
                        1387,
                        955
                    ],
                    [
                        1384,
                        952
                    ],
                    [
                        1383,
                        952
                    ],
                    [
                        1379,
                        948
                    ],
                    [
                        1378,
                        948
                    ],
                    [
                        1375,
                        945
                    ],
                    [
                        1374,
                        945
                    ],
                    [
                        1370,
                        941
                    ],
                    [
                        1369,
                        941
                    ],
                    [
                        1366,
                        938
                    ],
                    [
                        1365,
                        938
                    ],
                    [
                        1362,
                        935
                    ],
                    [
                        1361,
                        935
                    ],
                    [
                        1359,
                        933
                    ],
                    [
                        1358,
                        933
                    ],
                    [
                        1357,
                        932
                    ],
                    [
                        1354,
                        932
                    ],
                    [
                        1353,
                        931
                    ],
                    [
                        1351,
                        931
                    ],
                    [
                        1350,
                        930
                    ],
                    [
                        1348,
                        930
                    ],
                    [
                        1347,
                        929
                    ],
                    [
                        1344,
                        929
                    ],
                    [
                        1343,
                        928
                    ],
                    [
                        1341,
                        928
                    ],
                    [
                        1340,
                        927
                    ],
                    [
                        1338,
                        927
                    ],
                    [
                        1337,
                        926
                    ],
                    [
                        1334,
                        926
                    ],
                    [
                        1333,
                        925
                    ]
                ],
                "interior": []
            }
        },
        {
            "id": 16355783,
            "classId": 28372,
            "description": "",
            "geometryType": "rectangle",
            "labelerLogin": "seryios.sych@gmail.com",
            "createdAt": "2023-08-06T16:57:10.881Z",
            "updatedAt": "2023-08-06T16:57:10.881Z",
            "tags": [],
            "classTitle": "apple_red_boskoop",
            "points": {
                "exterior": [
                    [
                        1208,
                        925
                    ],
                    [
                        1417,
                        1159
                    ]
                ],
                "interior": []
            }
        }
    ]
}